sber_payments/__init__.py
sber_payments/client.py
sber_payments/exceptions.py
sber_payments-0.3.0.dist-info/LICENSE.txt
sber_payments-0.3.0.dist-info/METADATA
sber_payments-0.3.0.dist-info/WHEEL
sber_payments-0.3.0.dist-info/top_level.txt
sber_payments-0.3.0.dist-info/RECORD
